Metadata-Version: 2.1
Name: cryptome
Version: 0.0.1
Summary: Get crypto price & info fast, no API needed!
Home-page: UNKNOWN
Author: Neil Shah
Author-email: neil@insight3d.tech
License: MIT
Keywords: crypto
Platform: UNKNOWN
Classifier: Development Status :: 5 - Production/Stable
Classifier: Intended Audience :: Education
Classifier: Operating System :: Microsoft :: Windows :: Windows 10
Classifier: License :: OSI Approved :: MIT License
Classifier: Programming Language :: Python :: 3
